setup.py
commenttools/__init__.py
commenttools/moderation.py
glamkit_commenttools.egg-info/PKG-INFO
glamkit_commenttools.egg-info/SOURCES.txt
glamkit_commenttools.egg-info/dependency_links.txt
glamkit_commenttools.egg-info/not-zip-safe
glamkit_commenttools.egg-info/top_level.txt