Metadata-Version: 1.0
Name: glamkit-commenttools
Version: 0.5.1
Summary: Useful bits to spice up comments in your Django site.
Home-page: http://github.com/glamkit/glamkit-commenttools
Author: Julien Phalip
Author-email: julien@interaction.net.au
License: UNKNOWN
Platform: UNKNOWN
Classifier: Development Status :: 4 - Beta
Classifier: Environment :: Web Environment
Classifier: Intended Audience :: Developers
Classifier: License :: OSI Approved :: BSD License
Classifier: Operating System :: OS Independent
Classifier: Programming Language :: Python
Classifier: Framework :: Django
